pipmap/__init__.py
pipmap/mapper.py
pipmap-0.0.5.dist-info/LICENSE
pipmap-0.0.5.dist-info/METADATA
pipmap-0.0.5.dist-info/WHEEL
pipmap-0.0.5.dist-info/top_level.txt
pipmap-0.0.5.dist-info/RECORD
